Metadata-Version: 2.1
Name: pytest-boilerplate
Version: 0.7.0
Summary: The pytest plugin for your devxhub_python templates. 🍪
Home-page: https://github.com/devxhub/pytest-boilerplate
Author: DEVxHUB
Author-email: tech@devxhub.com
Maintainer: DEVxHUB
Maintainer-email: tech@devxhub.com
License: MIT
Project-URL: Repository, https://github.com/devxhub/pytest-boilerplate
Project-URL: Issues, https://github.com/devxhub/pytest-boilerplate/issues
Keywords: devxhub_python,pytest
Classifier: Development Status :: 5 - Production/Stable
Classifier: Intended Audience :: Developers
Classifier: License :: OSI Approved :: MIT License
Classifier: Operating System :: OS Independent
Classifier: Programming Language :: Python :: 3 :: Only
Classifier: Programming Language :: Python :: 3.7
Classifier: Programming Language :: Python :: 3.8
Classifier: Programming Language :: Python :: 3.9
Classifier: Programming Language :: Python :: 3.10
Classifier: Programming Language :: Python :: 3.11
Classifier: Programming Language :: Python :: Implementation :: CPython
Classifier: Programming Language :: Python
Classifier: Topic :: Software Development :: Testing
Classifier: Framework :: Pytest
Requires-Python: >=3.7
License-File: LICENSE
Requires-Dist: devxhub-python>=0.5.0
Requires-Dist: pytest>=3.9.0
